rousepull.py
rousepull-0.0.0.dist-info/METADATA
rousepull-0.0.0.dist-info/WHEEL
rousepull-0.0.0.dist-info/licenses/LICENSE
rousepull-0.0.0.dist-info/RECORD
