Metadata-Version: 2.1
Name: rousepull
Version: 0.0.0
Summary: Inference for locus pulling, based on the Rouse model
Project-URL: Homepage, https://github.com/OpenTrajectoryAnalysis/rousepull
Project-URL: Documentation, https://rousepull.readthedocs.org/en/latest
Project-URL: Bug Tracker, https://github.com/OpenTrajectoryAnalysis/rousepull/issues
Author-email: Simon Grosse-Holz <sgh256@mit.edu>
License: MIT License
License-File: LICENSE
Classifier: License :: OSI Approved :: MIT License
Classifier: Operating System :: OS Independent
Classifier: Programming Language :: Python :: 3
Requires-Python: >=3.7
Requires-Dist: numpy>=1.20
Requires-Dist: scipy>=1.6
